tinyOpenAI/__init__.py
tinyOpenAI/tinyOpenAI.py
tinyOpenAI-0.13.dist-info/LICENSE
tinyOpenAI-0.13.dist-info/METADATA
tinyOpenAI-0.13.dist-info/WHEEL
tinyOpenAI-0.13.dist-info/entry_points.txt
tinyOpenAI-0.13.dist-info/top_level.txt
tinyOpenAI-0.13.dist-info/RECORD
