Metadata-Version: 2.1
Name: tinyOpenAI
Version: 0.13
Summary: Tiny OpenAI ChatGPT and Whisper API Library
Home-page: https://github.com/wolf71/tinyOpenAI
Author: Charles Lai
Author-email: 
License: UNKNOWN
Platform: UNKNOWN
Classifier: Programming Language :: Python :: 3
Classifier: License :: OSI Approved :: MIT License
Classifier: Operating System :: OS Independent
License-File: LICENSE
Requires-Dist: requests
